MANIFEST.in
setup.cfg
setup.py
nbjekyll/__init__.py
nbjekyll/convert_nbs.py
nbjekyll.egg-info/PKG-INFO
nbjekyll.egg-info/SOURCES.txt
nbjekyll.egg-info/dependency_links.txt
nbjekyll.egg-info/not-zip-safe
nbjekyll.egg-info/requires.txt
nbjekyll.egg-info/top_level.txt
nbjekyll/jekyllconvert/__init__.py
nbjekyll/jekyllconvert/jekyll_export.py
nbjekyll/jekyllconvert/templates/Jekyll_template.tpl
nbjekyll/nb_git/__init__.py
nbjekyll/nb_git/nb_git.py
nbjekyll/nb_git/tests/__init__.py
nbjekyll/nb_git/tests/base.py
nbjekyll/nb_git/tests/test_repo.py