Metadata-Version: 1.1
Name: nbjekyll
Version: 0.1.1
Summary: Package used for easy conversion from Jupyter notebook to Jekyll posts
Home-page: https://github.com/trallard/nbconvert-jekyllconvert.git
Author: Tania Allard
Author-email: t.allard@sheffield.ac.uk
License: MIT
Keywords: jekyll,nbconvert,jupyternotebooks
Platform: UNKNOWN
Classifier: Programming Language :: Python :: 3
Classifier: Development Status :: 4 - Beta
Classifier: Intended Audience :: Education
Classifier: License :: OSI Approved :: MIT License
